unix_perms/__init__.py
unix_perms/exceptions.py
unix_perms/models.py
unix_perms/octals.py
unix_perms/permissions.py
unix_perms/py.typed
unix_perms/types.py
unix_perms-0.5.0.dist-info/LICENSE
unix_perms-0.5.0.dist-info/METADATA
unix_perms-0.5.0.dist-info/WHEEL
unix_perms-0.5.0.dist-info/RECORD
