Metadata-Version: 2.1
Name: unix-perms
Version: 0.5.0
Summary: Manage and interpret Unix file permissions with a Python package that provides intuitive tools for creating, validating, and describing permission modes.
License: MIT
Keywords: unix,permissions,files,modes
Author: galactixx
Requires-Python: >=3.8,<4.0
Classifier: License :: OSI Approved :: MIT License
Classifier: Programming Language :: Python :: 3
Classifier: Programming Language :: Python :: 3.8
Classifier: Programming Language :: Python :: 3.9
Classifier: Programming Language :: Python :: 3.10
Classifier: Programming Language :: Python :: 3.11
Classifier: Programming Language :: Python :: 3.12
Requires-Dist: pydantic (>=2.7.1,<3.0.0)
